[
  {
    "line": 1,
    "elements": [
      {
        "start_timestamp": "2023-04-09T13:31:24.729Z",
        "line": 14,
        "name": "user can see the consumer and business tel number",
        "description": "",
        "id": "credit-card-inquiries-us-bank-phone-numbers;user-can-see-the-consumer-and-business-tel-number;;2",
        "after": [
          {
            "result": {
              "duration": 98628000,
              "status": "passed"
            },
            "match": {
              "location": "StateFarmStepDefinition.StepDefinitions.tearDown()"
            }
          }
        ],
        "type": "scenario",
        "keyword": "Scenario Outline",
        "steps": [
          {
            "result": {
              "duration": 34094033000,
              "status": "passed"
            },
            "line": 4,
            "name": "I am on StateFarm homepage",
            "match": {
              "location": "StateFarmStepDefinition.StepDefinitions.iAmOnStateFarmHomepage()"
            },
            "keyword": "Given "
          },
          {
            "result": {
              "duration": 47092000,
              "status": "passed"
            },
            "line": 5,
            "name": "I scroll to the bottom of the page",
            "match": {
              "location": "StateFarmStepDefinition.StepDefinitions.iScrollToTheBottomOfThePage()"
            },
            "keyword": "When "
          },
          {
            "result": {
              "duration": 3300122000,
              "status": "passed"
            },
            "line": 6,
            "name": "clicks the contact us link",
            "match": {
              "location": "StateFarmStepDefinition.StepDefinitions.clicksTheContactUpLink()"
            },
            "keyword": "And "
          },
          {
            "result": {
              "duration": 3417000,
              "status": "passed"
            },
            "line": 7,
            "name": "I should be taken to the contact us page",
            "match": {
              "location": "StateFarmStepDefinition.StepDefinitions.iShouldBeTakenToTheContactUsPage()"
            },
            "keyword": "Then "
          },
          {
            "result": {
              "duration": 29017000,
              "status": "passed"
            },
            "line": 8,
            "name": "In the Credit card inquiries - U.S. Bank section I should see the consumer tel as \"833-728-0344\"",
            "match": {
              "arguments": [
                {
                  "val": "\"833-728-0344\"",
                  "offset": 82
                }
              ],
              "location": "StateFarmStepDefinition.StepDefinitions.inTheCreditCardInquiriesUSBankSectionIShouldSeeTheConsumerTelAs(java.lang.String)"
            },
            "keyword": "Then "
          },
          {
            "result": {
              "duration": 19733000,
              "status": "passed"
            },
            "line": 9,
            "name": "The business tel number as \"833-728-0345\"",
            "match": {
              "arguments": [
                {
                  "val": "\"833-728-0345\"",
                  "offset": 27
                }
              ],
              "location": "StateFarmStepDefinition.StepDefinitions.theBusinessTelNumberAs(java.lang.String)"
            },
            "keyword": "And "
          }
        ]
      }
    ],
    "name": "Credit Card Inquiries US Bank Phone Numbers",
    "description": "",
    "id": "credit-card-inquiries-us-bank-phone-numbers",
    "keyword": "Feature",
    "uri": "file:src/main/java/StateFarmFeature/ContactUs.feature",
    "tags": []
  },
  {
    "line": 1,
    "elements": [
      {
        "start_timestamp": "2023-04-09T13:32:02.362Z",
        "line": 3,
        "name": "Clicking help button would take to the customer care page",
        "description": "",
        "id": "help-button-redirects-to-customer-care-page;clicking-help-button-would-take-to-the-customer-care-page",
        "after": [
          {
            "result": {
              "duration": 110217000,
              "status": "passed"
            },
            "match": {
              "location": "StateFarmStepDefinition.StepDefinitions.tearDown()"
            }
          }
        ],
        "type": "scenario",
        "keyword": "Scenario",
        "steps": [
          {
            "result": {
              "duration": 25397363000,
              "status": "passed"
            },
            "line": 4,
            "name": "I am on StateFarm homepage",
            "match": {
              "location": "StateFarmStepDefinition.StepDefinitions.iAmOnStateFarmHomepage()"
            },
            "keyword": "Given "
          },
          {
            "result": {
              "duration": 5082998000,
              "status": "passed"
            },
            "line": 5,
            "name": "I click on the help button",
            "match": {
              "location": "StateFarmStepDefinition.StepDefinitions.iClickOnTheHelpButton()"
            },
            "keyword": "When "
          },
          {
            "result": {
              "duration": 5812000,
              "status": "passed"
            },
            "line": 6,
            "name": "I should be taken to the customer care page",
            "match": {
              "location": "StateFarmStepDefinition.StepDefinitions.iShouldBeTakenToTheCustomerCarePage()"
            },
            "keyword": "Then "
          }
        ]
      }
    ],
    "name": "Help button redirects to Customer Care Page",
    "description": "",
    "id": "help-button-redirects-to-customer-care-page",
    "keyword": "Feature",
    "uri": "file:src/main/java/StateFarmFeature/Help.feature",
    "tags": []
  },
  {
    "line": 1,
    "elements": [
      {
        "start_timestamp": "2023-04-09T13:32:32.967Z",
        "line": 10,
        "name": "",
        "description": "",
        "id": "support-for-spanish-language-on-the-website;;;2",
        "after": [
          {
            "result": {
              "duration": 89800000,
              "status": "passed"
            },
            "match": {
              "location": "StateFarmStepDefinition.StepDefinitions.tearDown()"
            }
          }
        ],
        "type": "scenario",
        "keyword": "Scenario Outline",
        "steps": [
          {
            "result": {
              "duration": 22141300000,
              "status": "passed"
            },
            "line": 4,
            "name": "I am on StateFarm homepage",
            "match": {
              "location": "StateFarmStepDefinition.StepDefinitions.iAmOnStateFarmHomepage()"
            },
            "keyword": "Given "
          },
          {
            "result": {
              "duration": 6346666000,
              "status": "passed"
            },
            "line": 5,
            "name": "I click on the epsanol button",
            "match": {
              "location": "StateFarmStepDefinition.StepDefinitions.iClickOnTheEpsanolButton()"
            },
            "keyword": "When "
          },
          {
            "result": {
              "duration": 21821000,
              "status": "passed"
            },
            "line": 6,
            "name": "I should see the website language changed to spanish by checking the \"Crea un precio económico, solo para ti.\"",
            "match": {
              "arguments": [
                {
                  "val": "\"Crea un precio económico, solo para ti.\"",
                  "offset": 69
                }
              ],
              "location": "StateFarmStepDefinition.StepDefinitions.iShouldSeeTheWebsiteLanguageChangedToSpanishByCheckingThe(java.lang.String)"
            },
            "keyword": "Then "
          }
        ]
      }
    ],
    "name": "Support for spanish language on the website",
    "description": "",
    "id": "support-for-spanish-language-on-the-website",
    "keyword": "Feature",
    "uri": "file:src/main/java/StateFarmFeature/Multilingualism.feature",
    "tags": []
  },
  {
    "line": 1,
    "elements": [
      {
        "start_timestamp": "2023-04-09T13:33:01.575Z",
        "line": 12,
        "name": "When user searches \"Auto insurance\" keyword, they should see more than one search result",
        "description": "",
        "id": "user-can-search-anything-on-the-site;when-user-searches-\"auto-insurance\"-keyword--they-should-see-more-than-one-search-result;;2",
        "after": [
          {
            "result": {
              "duration": 96911000,
              "status": "passed"
            },
            "match": {
              "location": "StateFarmStepDefinition.StepDefinitions.tearDown()"
            }
          }
        ],
        "type": "scenario",
        "keyword": "Scenario Outline",
        "steps": [
          {
            "result": {
              "duration": 22113088000,
              "status": "passed"
            },
            "line": 4,
            "name": "I am on StateFarm homepage",
            "match": {
              "location": "StateFarmStepDefinition.StepDefinitions.iAmOnStateFarmHomepage()"
            },
            "keyword": "Given "
          },
          {
            "result": {
              "duration": 33268000,
              "status": "passed"
            },
            "line": 5,
            "name": "I click on the search link",
            "match": {
              "location": "StateFarmStepDefinition.StepDefinitions.iClickOnTheSearchLink()"
            },
            "keyword": "When "
          },
          {
            "result": {
              "duration": 2242584000,
              "status": "passed"
            },
            "line": 6,
            "name": "I enter \"Auto insurance\" to search and click the search button",
            "match": {
              "arguments": [
                {
                  "val": "\"Auto insurance\"",
                  "offset": 8
                }
              ],
              "location": "StateFarmStepDefinition.StepDefinitions.iEnterToSearchAndClickTheSearchButton(java.lang.String)"
            },
            "keyword": "And "
          },
          {
            "result": {
              "duration": 5015000,
              "status": "passed"
            },
            "line": 7,
            "name": "I should be taken to the search result page",
            "match": {
              "location": "StateFarmStepDefinition.StepDefinitions.iShouldBeTakenToTheSearchResultPage()"
            },
            "keyword": "Then "
          },
          {
            "result": {
              "duration": 1337242000,
              "status": "passed"
            },
            "line": 8,
            "name": "There I can verify that more than one search result for the keyword is shown",
            "match": {
              "location": "StateFarmStepDefinition.StepDefinitions.thereICanVerifyThatMoreThanOneSearchResultForTheKeywordIsShown()"
            },
            "keyword": "And "
          }
        ]
      }
    ],
    "name": "User can search anything on the site",
    "description": "",
    "id": "user-can-search-anything-on-the-site",
    "keyword": "Feature",
    "uri": "file:src/main/java/StateFarmFeature/Searching.feature",
    "tags": []
  },
  {
    "line": 1,
    "elements": [
      {
        "start_timestamp": "2023-04-09T13:33:27.413Z",
        "line": 12,
        "name": "User clicks next button on the homepage Discover more articles carousel and after seeing the calculator card",
        "description": "    they clicks it. This will take them to a new tab containing the calculator page",
        "id": "homepage-discover-more-articles-carousel-has-calculator-card.-when-users-clicks-on-the-card--they-should-be-taken-to-the-calculator-page;user-clicks-next-button-on-the-homepage-discover-more-articles-carousel-and-after-seeing-the-calculator-card;;2",
        "after": [
          {
            "result": {
              "duration": 112561000,
              "status": "passed"
            },
            "match": {
              "location": "StateFarmStepDefinition.StepDefinitions.tearDown()"
            }
          }
        ],
        "type": "scenario",
        "keyword": "Scenario Outline",
        "steps": [
          {
            "result": {
              "duration": 20190040000,
              "status": "passed"
            },
            "line": 5,
            "name": "I am on StateFarm homepage",
            "match": {
              "location": "StateFarmStepDefinition.StepDefinitions.iAmOnStateFarmHomepage()"
            },
            "keyword": "Given "
          },
          {
            "result": {
              "duration": 13348000,
              "status": "passed"
            },
            "line": 6,
            "name": "I scroll to the discover more articles sections",
            "match": {
              "location": "StateFarmStepDefinition.StepDefinitions.iScrollToTheDiscoverMoreArticlesSections()"
            },
            "keyword": "When "
          },
          {
            "result": {
              "duration": 28709062000,
              "status": "passed"
            },
            "line": 7,
            "name": "clicks the next button until the calculator card is being displayed and clicks the card",
            "match": {
              "location": "StateFarmStepDefinition.StepDefinitions.clicksTheNextButtonUntilTheCalculatorCardIsBeingDisplayedAndClicksTheCard()"
            },
            "keyword": "And "
          },
          {
            "result": {
              "duration": 8427000,
              "status": "passed"
            },
            "line": 8,
            "name": "I should be taken to the calculator page whose url should be as \"https://www.statefarm.com/simple-insights/calculators\"",
            "match": {
              "arguments": [
                {
                  "val": "\"https://www.statefarm.com/simple-insights/calculators\"",
                  "offset": 64
                }
              ],
              "location": "StateFarmStepDefinition.StepDefinitions.iShouldBeTakenToTheCalculatorPageWhoseUrlShouldBeAs(java.lang.String)"
            },
            "keyword": "Then "
          }
        ]
      }
    ],
    "name": "Homepage Discover more articles carousel has calculator card. When users clicks on the card, they should be taken to the calculator page",
    "description": "",
    "id": "homepage-discover-more-articles-carousel-has-calculator-card.-when-users-clicks-on-the-card--they-should-be-taken-to-the-calculator-page",
    "keyword": "Feature",
    "uri": "file:src/main/java/StateFarmFeature/StateFarmCalculator.feature",
    "tags": []
  }
]